mqttapi/EventSource.py
mqttapi/MysqlBD.py
mqttapi/__init__.py
mqttapi/__version__.py
mqttapi/bd_manipulator.py
mqttapi/json_manipulator.py
mqttapi/mqtt_communicator.py
mqttapi/t2.py
mqttapi/websocket_client.py
mqttapi/websocket_server.py
mqttapi-0.4.4.dist-info/LICENSE
mqttapi-0.4.4.dist-info/METADATA
mqttapi-0.4.4.dist-info/WHEEL
mqttapi-0.4.4.dist-info/top_level.txt
mqttapi-0.4.4.dist-info/RECORD
