Metadata-Version: 2.1
Name: mqttapi
Version: 0.4.4
Summary: simplified mqtt library
Home-page: https://github.com/davisouzaluna/mqttapi
Author: Davi Luna
Author-email: Sdavi738@gmail.com
Keywords: mqtt api,mosquitto api,real-time,messaging,simplified mqtt,paho-mqtt api,MQTT,mqtt
Classifier: Development Status :: 2 - Pre-Alpha
Classifier: Intended Audience :: Developers
Classifier: License :: OSI Approved :: MIT License
Classifier: Programming Language :: Python :: 3
Classifier: Programming Language :: Python :: 3.7
Classifier: Programming Language :: Python :: 3.8
Classifier: Programming Language :: Python :: 3.9
License-File: LICENSE
Requires-Dist: mysql-connector-python
Requires-Dist: paho-mqtt
Requires-Dist: asyncio
Requires-Dist: websockets
Requires-Dist: websocket
